quantscripts/CointegrationTest .py
quantscripts/ConstructingComprehensive.py
quantscripts/Duration.py
quantscripts/StatisticalFeatures.py
quantscripts/__init__.py
quantscripts-0.1.5.dist-info/METADATA
quantscripts-0.1.5.dist-info/WHEEL
quantscripts-0.1.5.dist-info/top_level.txt
quantscripts-0.1.5.dist-info/RECORD
