Metadata-Version: 2.1
Name: quantscripts
Version: 0.1.5
Summary: A package for calculating statistical data in finance
Home-page: https://github.com/tonyyang1223/quantscripts.git
Author: tonyyang1223
Author-email: tonyyang1223@gmail.com
License: MIT
Project-URL: Source, https://github.com/tonyyang1223/quantscripts.git
Requires-Dist: pandas
Requires-Dist: numpy
Requires-Dist: statsmodels
Requires-Dist: matplotlib
Requires-Dist: scipy
